{
    "guid": "1086417563444232194_twitter",
    "gt_cls": 1,
    "coalitions": [
        [
            "<user>",
            "let",
            "be",
            "honest",
            "multiculturalism",
            "is",
            "just",
            "a",
            "euphemism",
            "for",
            "hostile",
            "takeover",
            "by",
            "jews",
            "and",
            "non",
            "whites"
        ],
        [
            "<user>",
            "let",
            "be",
            "honest",
            "multiculturalism"
        ],
        [
            "is",
            "just",
            "a",
            "euphemism",
            "for",
            "hostile",
            "takeover",
            "by",
            "jews",
            "and",
            "non",
            "whites"
        ],
        [
            "<user>"
        ],
        [
            "let",
            "be",
            "honest",
            "multiculturalism"
        ],
        [
            "is"
        ],
        [
            "just",
            "a",
            "euphemism",
            "for",
            "hostile",
            "takeover",
            "by",
            "jews",
            "and",
            "non",
            "whites"
        ],
        [
            "let"
        ],
        [
            "be",
            "honest",
            "multiculturalism"
        ],
        [
            "just",
            "a",
            "euphemism"
        ],
        [
            "for",
            "hostile",
            "takeover",
            "by",
            "jews",
            "and",
            "non",
            "whites"
        ],
        [
            "be",
            "honest",
            "multiculturalism"
        ],
        [
            "just"
        ],
        [
            "a"
        ],
        [
            "euphemism"
        ],
        [
            "for"
        ],
        [
            "hostile",
            "takeover",
            "by",
            "jews",
            "and",
            "non",
            "whites"
        ],
        [
            "be"
        ],
        [
            "honest",
            "multiculturalism"
        ],
        [
            "hostile",
            "takeover"
        ],
        [
            "by",
            "jews",
            "and",
            "non",
            "whites"
        ],
        [
            "honest"
        ],
        [
            "multiculturalism"
        ],
        [
            "hostile"
        ],
        [
            "takeover"
        ],
        [
            "by"
        ],
        [
            "jews",
            "and",
            "non",
            "whites"
        ],
        [
            "jews"
        ],
        [
            "and"
        ],
        [
            "non",
            "whites"
        ],
        [
            "non"
        ],
        [
            "whites"
        ]
    ],
    "value_func": [
        1.0000000085484035,
        0.36150721204781605,
        0.6384156239170817,
        0.0637400738893296,
        0.2976055824126588,
        0.03325351266765876,
        0.6051576697501754,
        0.07192781479471703,
        0.2255299054974159,
        0.15464282125067075,
        0.45048707459616716,
        0.2255222878846213,
        0.025746925807312193,
        0.02245816319389172,
        0.1063684481060315,
        0.022804469136118753,
        0.4275822439687848,
        0.04714449045121069,
        0.17837017982061604,
        0.09400882028831299,
        0.33344414292420604,
        0.05926522850687001,
        0.11899854874974511,
        0.03616133396758094,
        0.057698618435207016,
        0.032052109726989186,
        0.3013299788112865,
        0.1210017905411804,
        0.0351032070978935,
        0.14518468118340444,
        0.057069615606124016,
        0.08770257744238473
    ],
    "dividend_dir": [
        -1,
        -1,
        1,
        -1,
        -1,
        -1,
        1,
        -1,
        1,
        -1,
        1,
        1,
        -1,
        -1,
        1,
        -1,
        1,
        -1,
        1,
        1,
        1,
        -1,
        1,
        1,
        1,
        1,
        1,
        -1,
        1,
        1,
        1,
        1
    ],
    "p_tree": [
        [
            null,
            0
        ],
        [
            0,
            1
        ],
        [
            0,
            2
        ],
        [
            1,
            3
        ],
        [
            1,
            4
        ],
        [
            2,
            5
        ],
        [
            2,
            6
        ],
        [
            4,
            7
        ],
        [
            4,
            8
        ],
        [
            6,
            9
        ],
        [
            6,
            10
        ],
        [
            8,
            11
        ],
        [
            9,
            12
        ],
        [
            9,
            13
        ],
        [
            9,
            14
        ],
        [
            10,
            15
        ],
        [
            10,
            16
        ],
        [
            11,
            17
        ],
        [
            11,
            18
        ],
        [
            16,
            19
        ],
        [
            16,
            20
        ],
        [
            18,
            21
        ],
        [
            18,
            22
        ],
        [
            19,
            23
        ],
        [
            19,
            24
        ],
        [
            20,
            25
        ],
        [
            20,
            26
        ],
        [
            26,
            27
        ],
        [
            26,
            28
        ],
        [
            26,
            29
        ],
        [
            29,
            30
        ],
        [
            29,
            31
        ]
    ]
}