{
    "guid": "1178264675663929346_twitter",
    "gt_cls": 0,
    "coalitions": [
        [
            "<user>",
            "is",
            "it",
            "colored",
            "or",
            "black",
            "and",
            "white",
            "and1",
            "make",
            "sure",
            "it1",
            "has",
            "red",
            "background"
        ],
        [
            "<user>"
        ],
        [
            "is",
            "it",
            "colored",
            "or",
            "black",
            "and",
            "white",
            "and1",
            "make",
            "sure",
            "it1",
            "has",
            "red",
            "background"
        ],
        [
            "is",
            "it",
            "colored",
            "or",
            "black",
            "and",
            "white"
        ],
        [
            "and1"
        ],
        [
            "make",
            "sure",
            "it1",
            "has",
            "red",
            "background"
        ],
        [
            "is"
        ],
        [
            "it",
            "colored",
            "or",
            "black",
            "and",
            "white"
        ],
        [
            "make"
        ],
        [
            "sure",
            "it1",
            "has",
            "red",
            "background"
        ],
        [
            "it"
        ],
        [
            "colored",
            "or",
            "black",
            "and",
            "white"
        ],
        [
            "sure"
        ],
        [
            "it1",
            "has",
            "red",
            "background"
        ],
        [
            "colored"
        ],
        [
            "or"
        ],
        [
            "black"
        ],
        [
            "and"
        ],
        [
            "white"
        ],
        [
            "it1",
            "has",
            "red",
            "background"
        ],
        [
            "it1"
        ],
        [
            "has",
            "red",
            "background"
        ],
        [
            "has"
        ],
        [
            "red",
            "background"
        ],
        [
            "red"
        ],
        [
            "background"
        ]
    ],
    "value_func": [
        1.0000000164590288,
        0.10300289753975331,
        0.8961720953828737,
        0.48669975687304395,
        0.046188484634382354,
        0.3625150289599802,
        0.0902516817657619,
        0.3956670552845961,
        0.05278080313511549,
        0.3094302029264186,
        0.08007727107243647,
        0.3148284841444439,
        0.054832122943429006,
        0.2542195683998729,
        0.10265783621311414,
        0.05657098516758668,
        0.06000950388837512,
        0.043813558435214055,
        0.051066033003302314,
        0.2536578214196527,
        0.04772088174959932,
        0.20537519268983315,
        0.05095355676040663,
        0.15395130317748895,
        0.0632398751762104,
        0.0903612844173714
    ],
    "dividend_dir": [
        1,
        1,
        1,
        1,
        1,
        1,
        1,
        1,
        -1,
        1,
        1,
        1,
        -1,
        1,
        1,
        1,
        1,
        1,
        1,
        1,
        1,
        1,
        1,
        1,
        1,
        1
    ],
    "p_tree": [
        [
            null,
            0
        ],
        [
            0,
            1
        ],
        [
            0,
            2
        ],
        [
            2,
            3
        ],
        [
            2,
            4
        ],
        [
            2,
            5
        ],
        [
            3,
            6
        ],
        [
            3,
            7
        ],
        [
            5,
            8
        ],
        [
            5,
            9
        ],
        [
            7,
            10
        ],
        [
            7,
            11
        ],
        [
            9,
            12
        ],
        [
            9,
            13
        ],
        [
            11,
            14
        ],
        [
            11,
            15
        ],
        [
            11,
            16
        ],
        [
            11,
            17
        ],
        [
            11,
            18
        ],
        [
            13,
            19
        ],
        [
            19,
            20
        ],
        [
            19,
            21
        ],
        [
            21,
            22
        ],
        [
            21,
            23
        ],
        [
            23,
            24
        ],
        [
            23,
            25
        ]
    ]
}